rplus_offline_result/__init__.py
rplus_offline_result_module-0.0.3.dist-info/WHEEL
rplus_offline_result_module-0.0.3.dist-info/METADATA
rplus_offline_result_module-0.0.3.dist-info/RECORD
